orchard_core.cpython-39-darwin.so
orchard/__init__.py
orchard/cli.py
orchard/loader.py
orchard/model.py
orchard/optimizer.py
orchard/quantizer.py
orchard/kernels/elementwise.metal
orchard/kernels/embedding.metal
orchard/kernels/gemm_int4.metal
orchard/kernels/gemv_int4.metal
orchard/kernels/gemv_int8.metal
orchard/kernels/matmul.metal
orchard/kernels/matmul_simd.metal
orchard/kernels/rmsnorm.metal
orchard/kernels/rope.metal
orchard/kernels/softmax.metal
orchard_llm-0.1.1.dist-info/licenses/LICENSE
orchard_llm-0.1.1.dist-info/METADATA
orchard_llm-0.1.1.dist-info/WHEEL
orchard_llm-0.1.1.dist-info/top_level.txt
orchard_llm-0.1.1.dist-info/RECORD
