Metadata-Version: 2.4
Name: orchard-llm
Version: 0.1.1
Summary: High-performance LLM runtime for Apple Silicon
Author: Orchard Team
Requires-Python: >=3.9
License-File: LICENSE
Requires-Dist: numpy
Requires-Dist: safetensors
Requires-Dist: tokenizers
Dynamic: author
Dynamic: license-file
Dynamic: requires-python
